akkord/__init__.py
akkord/cfg.py
akkord/err.py
akkord/reader.py
akkord/realtime.py
akkord/utils.py
akkord/writer.py
akkord-0.0.3.dist-info/LICENSE
akkord-0.0.3.dist-info/METADATA
akkord-0.0.3.dist-info/WHEEL
akkord-0.0.3.dist-info/top_level.txt
akkord-0.0.3.dist-info/RECORD
