Metadata-Version: 2.1
Name: akkord
Version: 0.0.3
Summary: Algorithmic Composition Utilities
Author-email: Amir Teymuri <amiratwork22@gmail.com>
License: GNU GENERAL PUBLIC LICENSE
Project-URL: Homepage, https://github.com/teymuri/akkord
Project-URL: Bug Tracker, https://github.com/teymuri/akkord/issues
Classifier: Programming Language :: Python :: 3
Classifier: License :: OSI Approved :: GNU Affero General Public License v3
Classifier: Operating System :: OS Independent
Requires-Python: >=3.5
License-File: LICENSE
Requires-Dist: python-rtmidi
Requires-Dist: MIDIUtil
Requires-Dist: mido
Requires-Dist: numpy
